owslib/__init__.py
owslib/crs.py
owslib/csw.py
owslib/dif.py
owslib/etree.py
owslib/fes.py
owslib/fes2.py
owslib/fgdc.py
owslib/gm03.py
owslib/gml.py
owslib/interfaces.py
owslib/iso.py
owslib/iso3.py
owslib/iso_che.py
owslib/namespaces.py
owslib/opensearch.py
owslib/ows.py
owslib/sos.py
owslib/tms.py
owslib/util.py
owslib/wcs.py
owslib/wfs.py
owslib/wmc.py
owslib/wms.py
owslib/wmts.py
owslib/wps.py
owslib/catalogue/__init__.py
owslib/catalogue/csw2.py
owslib/catalogue/csw3.py
owslib/coverage/__init__.py
owslib/coverage/wcs100.py
owslib/coverage/wcs110.py
owslib/coverage/wcs111.py
owslib/coverage/wcs200.py
owslib/coverage/wcs201.py
owslib/coverage/wcsBase.py
owslib/coverage/wcsdecoder.py
owslib/feature/__init__.py
owslib/feature/common.py
owslib/feature/postrequest.py
owslib/feature/schema.py
owslib/feature/wfs100.py
owslib/feature/wfs110.py
owslib/feature/wfs200.py
owslib/map/__init__.py
owslib/map/common.py
owslib/map/wms111.py
owslib/map/wms130.py
owslib/ogcapi/__init__.py
owslib/ogcapi/connectedsystems.py
owslib/ogcapi/coverages.py
owslib/ogcapi/edr.py
owslib/ogcapi/features.py
owslib/ogcapi/maps.py
owslib/ogcapi/processes.py
owslib/ogcapi/records.py
owslib/owscontext/__init__.py
owslib/owscontext/atom.py
owslib/owscontext/common.py
owslib/owscontext/core.py
owslib/owscontext/geojson.py
owslib/swe/__init__.py
owslib/swe/common.py
owslib/swe/observation/__init__.py
owslib/swe/observation/om.py
owslib/swe/observation/sos100.py
owslib/swe/observation/sos200.py
owslib/swe/observation/waterml2.py
owslib/swe/sensor/__init__.py
owslib/swe/sensor/sml.py
owslib/waterml/__init__.py
owslib/waterml/wml.py
owslib/waterml/wml10.py
owslib/waterml/wml11.py
owslib-0.34.0.dist-info/licenses/AUTHORS.rst
owslib-0.34.0.dist-info/licenses/LICENSE
owslib-0.34.0.dist-info/METADATA
owslib-0.34.0.dist-info/WHEEL
owslib-0.34.0.dist-info/top_level.txt
owslib-0.34.0.dist-info/RECORD
