Metadata-Version: 2.4
Name: OWSLib
Version: 0.34.0
Summary: OGC Web Service utility library
Home-page: https://owslib.readthedocs.io
Author: Sean Gillies
Author-email: sean.gillies@gmail.com
Maintainer: Tom Kralidis
Maintainer-email: tomkralidis@gmail.com
License: BSD
Keywords: gis ogc ogcapi ows opensearch iso 19115 fgdc dif ows wfs wms sos csw wps wcs capabilities metadata wmts connectedsystems
Classifier: Development Status :: 4 - Beta
Classifier: Intended Audience :: Developers
Classifier: Intended Audience :: Science/Research
Classifier: License :: OSI Approved :: BSD License
Classifier: Natural Language :: English
Classifier: Operating System :: OS Independent
Classifier: Programming Language :: Python
Classifier: Topic :: Scientific/Engineering :: GIS
Requires-Python: >=3.10
License-File: LICENSE
License-File: AUTHORS.rst
Requires-Dist: lxml
Requires-Dist: python-dateutil
Requires-Dist: pyyaml
Requires-Dist: requests
Dynamic: author
Dynamic: author-email
Dynamic: classifier
Dynamic: description
Dynamic: description-content-type
Dynamic: home-page
Dynamic: keywords
Dynamic: license
Dynamic: license-file
Dynamic: maintainer
Dynamic: maintainer-email
Dynamic: requires-dist
Dynamic: requires-python
Dynamic: summary
